[
    {
        "model": "harmoniousapi.soundscape",
        "pk": 1,
        "fields": {
            "user": 1,
            "title": "Coffee Shop Vibes",
            "chordTexture": 2,
            "melodyNotes": "00023240",
            "melodyTexture": 1
        }
    },
    {
        "model": "harmoniousapi.soundscape",
        "pk": 2,
        "fields": {
            "user": 1,
            "title": "Astronaut's Regret",
            "chordTexture": 1,
            "melodyNotes": "03480020",
            "melodyTexture": 2
        }
    }
]
